hailolibero/__init__.py
hailolibero/hailolibero.py
hailolibero-0.0.1.dist-info/LICENSE
hailolibero-0.0.1.dist-info/METADATA
hailolibero-0.0.1.dist-info/WHEEL
hailolibero-0.0.1.dist-info/top_level.txt
hailolibero-0.0.1.dist-info/RECORD
