Metadata-Version: 2.1
Name: hailolibero
Version: 0.0.1
Summary: Python library to interface with the Hailo Libero 3.0
Author-email: Nick Dawson <nick@dawson.au>
Project-URL: Homepage, https://github.com/Neonkoala/hailolibero
Project-URL: Bug Tracker, https://github.com/Neonkoala/hailolibero/issues
Classifier: Programming Language :: Python :: 3
Classifier: License :: OSI Approved :: MIT License
Classifier: Operating System :: OS Independent
Requires-Python: >=3.7
License-File: LICENSE
